csvwrpr.py
csvwrpr-1.17.0.dist-info/METADATA
csvwrpr-1.17.0.dist-info/WHEEL
csvwrpr-1.17.0.dist-info/licenses/LICENSE.txt
csvwrpr-1.17.0.dist-info/RECORD
