Metadata-Version: 2.4
Name: CsvWrpr
Version: 1.17.0
Summary: CSv wrapper
License-Expression: MIT
License-File: LICENSE.txt
Author: Hendrik du Toit
Author-email: hendrik@brightedge.co.za
Maintainer: Hendrik du Toit
Maintainer-email: hendrikdt@citiqprepaid.co.za
Requires-Python: >=3.10
Classifier: Development Status :: 4 - Beta
Classifier: Intended Audience :: Developers
Classifier: Intended Audience :: Information Technology
Classifier: Intended Audience :: System Administrators
Classifier: License :: OSI Approved :: MIT License
Classifier: Programming Language :: Python :: 3.10
Classifier: Programming Language :: Python :: 3.11
Classifier: Programming Language :: Python :: 3.12
Classifier: Programming Language :: Python :: 3.13
Classifier: Topic :: Software Development :: Libraries :: Python Modules
Classifier: Topic :: System :: Archiving :: Packaging
Requires-Dist: beetools (>=5.2.4,<6.0.0)
Requires-Dist: displayfx (>=2.1.1,<3.0.0)
Project-URL: Homepage, https://github.com/BrightEdgeeServices/CsvWrpr
Project-URL: Repository, https://github.com/BrightEdgeeServices/CsvWrpr.git
Project-URL: changelog, https://github.com/BrightEdgeeServices/CsvWrpr/releases
Project-URL: issues, https://github.com/BrightEdgeeServices/CsvWrpr/issues
